pip2df/LICENSE
pip2df/README.MD
pip2df/__init__.py
pip2df/requirements.txt
pip2df/thirdparty.json
pip2df-0.11.dist-info/LICENSE.rst
pip2df-0.11.dist-info/METADATA
pip2df-0.11.dist-info/WHEEL
pip2df-0.11.dist-info/top_level.txt
pip2df-0.11.dist-info/RECORD
