Metadata-Version: 2.1
Name: pip2df
Version: 0.11
Summary: Parses all imports and the imports of the imports of a py file into a Pandas DataFrame using pipdeptree/pipreqs/pip
Home-page: https://github.com/hansalemaos/pip2df
Author: Johannes Fischer
Author-email: <aulasparticularesdealemaosp@gmail.com>
License: MIT
Keywords: PIP,pipreqs,piptree,parse,imports
Classifier: Development Status :: 4 - Beta
Classifier: Programming Language :: Python :: 3 :: Only
Classifier: Programming Language :: Python :: 3.10
Classifier: Topic :: Scientific/Engineering :: Visualization
Classifier: Topic :: Software Development :: Libraries :: Python Modules
Classifier: Topic :: Utilities
License-File: LICENSE.rst
Requires-Dist: a-pandas-ex-apply-ignore-exceptions
Requires-Dist: a-pandas-ex-dillpickle
Requires-Dist: a-pandas-ex-plode-tool
Requires-Dist: cprinter
Requires-Dist: dill
Requires-Dist: flatten-everything
Requires-Dist: pandas
Requires-Dist: pipdeptree
Requires-Dist: pipreqs
Requires-Dist: touchtouch
